gisea/__init__.py
gisea/__version__.py
gisea/classification.py
gisea/data.py
gisea/heatmap.py
gisea/run.py
gisea/search.py
gisea/setup_plots.py
gisea/utils.py
GISEA-0.1.1.dist-info/LICENSE
GISEA-0.1.1.dist-info/METADATA
GISEA-0.1.1.dist-info/WHEEL
GISEA-0.1.1.dist-info/top_level.txt
GISEA-0.1.1.dist-info/RECORD
