Metadata-Version: 2.1
Name: GISEA
Version: 0.1.1
Summary: Genetic Interaction Networks and Pathway Modules
Requires-Python: >=3.8
License-File: LICENSE
